plotpub.py
plotpub/__init__.py
plotpub/plotpub.py
plotpub-0.0.7.dist-info/LICENSE
plotpub-0.0.7.dist-info/METADATA
plotpub-0.0.7.dist-info/WHEEL
plotpub-0.0.7.dist-info/top_level.txt
plotpub-0.0.7.dist-info/RECORD
