Metadata-Version: 2.1
Name: plotpub
Version: 0.0.7
Summary: For publication quality plots
Home-page: https://github.com/samueljmcameron/plotpub
Author: Sam Cameron
Author-email: samuel.j.m.cameron@gmail.com
License: UNKNOWN
Platform: UNKNOWN
Classifier: Programming Language :: Python :: 3
Classifier: License :: OSI Approved :: GNU General Public License v3 (GPLv3)
Classifier: Operating System :: OS Independent
Requires-Python: >=3.6
Requires-Dist: matplotlib
Requires-Dist: numpy
